exencolor/__init__.py
exencolor/enums.py
exencolor-1.1.2.dist-info/LICENSE
exencolor-1.1.2.dist-info/WHEEL
exencolor-1.1.2.dist-info/METADATA
exencolor-1.1.2.dist-info/RECORD
