Metadata-Version: 2.1
Name: exencolor
Version: 1.1.2
Summary: A modern module for colored output.
Home-page: https://github.com/Exenifix/exencolor
License: MIT
Author: Exenifix
Requires-Python: >=3.10,<4.0
Classifier: License :: OSI Approved :: MIT License
Classifier: Programming Language :: Python :: 3
Classifier: Programming Language :: Python :: 3.10
Project-URL: Repository, https://github.com/Exenifix/exencolor
